README.txt
setup.py
DataCenter/__init__.py
DataCenter/DataSimulator/__init__.py
DataCenter/FuturesDataCrawler/FuturesCode.py
DataCenter/FuturesDataCrawler/FuturesDataCrawler.py
DataCenter/FuturesDataCrawler/__init__.py
DataCenter/WindApi/__init__.py
QuantGo.egg-info/PKG-INFO
QuantGo.egg-info/SOURCES.txt
QuantGo.egg-info/dependency_links.txt
QuantGo.egg-info/top_level.txt
QuantToolBox/BacktestTool.py
QuantToolBox/FuturesConfig.py
QuantToolBox/__init__.py