Metadata-Version: 1.1
Name: QuantGo
Version: 0.0.2
Summary: A powerful toolbox provides for quant
Home-page: https://github.com/Randomwak/QuantGO
Author: liaozechuan
Author-email: cloud.light@msn.cn
License:  Apache
Platform: all
Classifier: Development Status :: 3 - Alpha
Classifier: Intended Audience :: Developers
Classifier: Topic :: Software Development :: Libraries
Classifier: License :: OSI Approved :: Apache Software License
Classifier: Programming Language :: Python :: 2
Classifier: Programming Language :: Python :: 2.6
Classifier: Programming Language :: Python :: 2.7
Classifier: Programming Language :: Python :: 3
Classifier: Programming Language :: Python :: 3.5
Classifier: Programming Language :: Python :: 3.6
